{
  "id": "coding/excel",
  "title": "Excel",
  "description": "---",
  "source": "@site/docs/coding/excel.mdx",
  "sourceDirName": "coding",
  "slug": "/coding/excel",
  "permalink": "/docs/coding/excel",
  "draft": false,
  "unlisted": false,
  "editUrl": "https://github.com/ghi-electronics/duelink-website/tree/dev/docs/coding/excel.mdx",
  "tags": [],
  "version": "current",
  "frontMatter": {},
  "sidebar": "tutorialSidebar",
  "previous": {
    "title": "App Inventor",
    "permalink": "/docs/coding/app-inventor"
  },
  "next": {
    "title": "Other Languages",
    "permalink": "/docs/coding/other"
  }
}