{
  "id": "engine/standalone",
  "title": "Standalone",
  "description": "---",
  "source": "@site/docs/engine/standalone.mdx",
  "sourceDirName": "engine",
  "slug": "/engine/standalone",
  "permalink": "/docs/engine/standalone",
  "draft": false,
  "unlisted": false,
  "editUrl": "https://github.com/ghi-electronics/duelink-website/tree/dev/docs/engine/standalone.mdx",
  "tags": [],
  "version": "current",
  "frontMatter": {},
  "sidebar": "tutorialSidebar",
  "previous": {
    "title": "Scripting",
    "permalink": "/docs/engine/scripting"
  },
  "next": {
    "title": "Daisylink",
    "permalink": "/docs/engine/daisylink"
  }
}