{
  "id": "release-notes",
  "title": "Release Notes",
  "description": "---",
  "source": "@site/docs/release-notes.mdx",
  "sourceDirName": ".",
  "slug": "/release-notes",
  "permalink": "/docs/release-notes",
  "draft": false,
  "unlisted": false,
  "editUrl": "https://github.com/ghi-electronics/duelink-website/tree/dev/docs/release-notes.mdx",
  "tags": [],
  "version": "current",
  "frontMatter": {},
  "sidebar": "tutorialSidebar",
  "previous": {
    "title": "DUELink Downloads",
    "permalink": "/docs/downloads"
  },
  "next": {
    "title": "Support",
    "permalink": "/docs/support"
  }
}