{
  "id": "catalog/hmi/dial",
  "title": "Dial",
  "description": "---",
  "source": "@site/docs/catalog/hmi/dial.mdx",
  "sourceDirName": "catalog/hmi",
  "slug": "/catalog/hmi/dial",
  "permalink": "/docs/catalog/hmi/dial",
  "draft": false,
  "unlisted": false,
  "editUrl": "https://github.com/ghi-electronics/duelink-website/tree/dev/docs/catalog/hmi/dial.mdx",
  "tags": [],
  "version": "current",
  "frontMatter": {},
  "sidebar": "tutorialSidebar",
  "previous": {
    "title": "CapSlide",
    "permalink": "/docs/catalog/hmi/capslide"
  },
  "next": {
    "title": "Dip Switch",
    "permalink": "/docs/catalog/hmi/dip-switch"
  }
}