{
  "id": "api/bluetooth",
  "title": "Bluetooth",
  "description": "---",
  "source": "@site/docs/api/bluetooth.mdx",
  "sourceDirName": "api",
  "slug": "/api/bluetooth",
  "permalink": "/docs/api/bluetooth",
  "draft": false,
  "unlisted": false,
  "editUrl": "https://github.com/ghi-electronics/duelink-website/tree/dev/docs/api/bluetooth.mdx",
  "tags": [],
  "version": "current",
  "frontMatter": {},
  "sidebar": "tutorialSidebar",
  "previous": {
    "title": "Analog",
    "permalink": "/docs/api/analog"
  },
  "next": {
    "title": "Buttons",
    "permalink": "/docs/api/button"
  }
}