{
  "id": "interfaces/usb",
  "title": "USB",
  "description": "---",
  "source": "@site/docs/interfaces/usb.mdx",
  "sourceDirName": "interfaces",
  "slug": "/interfaces/usb",
  "permalink": "/duelink-website/docs/interfaces/usb",
  "draft": false,
  "unlisted": false,
  "editUrl": "https://ghi-electronics.github.io/duelink-website/docs/interfaces/usb.mdx",
  "tags": [],
  "version": "current",
  "frontMatter": {},
  "sidebar": "tutorialSidebar",
  "previous": {
    "title": "Interfaces",
    "permalink": "/duelink-website/docs/interfaces/intro"
  },
  "next": {
    "title": "I2C",
    "permalink": "/duelink-website/docs/interfaces/i2c"
  }
}