{
  "id": "catalog/com/serial-usb",
  "title": "Serial USB",
  "description": "---",
  "source": "@site/docs/catalog/com/serial-usb.mdx",
  "sourceDirName": "catalog/com",
  "slug": "/catalog/com/serial-usb",
  "permalink": "/docs/catalog/com/serial-usb",
  "draft": false,
  "unlisted": false,
  "editUrl": "https://github.com/ghi-electronics/duelink-website/tree/dev/docs/catalog/com/serial-usb.mdx",
  "tags": [],
  "version": "current",
  "frontMatter": {},
  "sidebar": "tutorialSidebar",
  "previous": {
    "title": "RS485",
    "permalink": "/docs/catalog/com/rs485"
  },
  "next": {
    "title": "USB Host",
    "permalink": "/docs/catalog/com/usb-host"
  }
}